DPRED/__init__.py
DPRED/blast.py
DPRED/get_pdb_data.py
DPRED/get_pdb_files.py
DPRED/get_uniprot_data.py
DPRED/hmm.py
DPRED/main.py
DPRED/msa.py
DPRED/performance.py
DPRED/remove.py
DPRED/validation.py
DPRED/src/Kabsch.h
DPRED/src/Makefile
DPRED/src/NW.h
DPRED/src/TMM.cpp
DPRED/src/TMM.h
DPRED/src/TMalign.h
DPRED/src/TMalign_main.h
DPRED/src/UPGMA.cpp
DPRED/src/UPGMA.h
DPRED/src/basic_fun.h
DPRED/src/mTM-align
DPRED/src/main.cpp
tests/__init__.py
tests/test_main.py
DPRED-1.0.4.dist-info/LICENSE
DPRED-1.0.4.dist-info/METADATA
DPRED-1.0.4.dist-info/WHEEL
DPRED-1.0.4.dist-info/entry_points.txt
DPRED-1.0.4.dist-info/top_level.txt
DPRED-1.0.4.dist-info/RECORD
