Metadata-Version: 2.1
Name: DPRED
Version: 1.0.4
Summary: DPRED is a softwares package for HMM domain prediction and validation
Home-page: https://github.com/dganci/DPRED
Author: Daniele Ganci
Author-email: daniele.ganci@studio.unibo.it
Classifier: Programming Language :: Python :: 3
Classifier: License :: OSI Approved :: MIT License
Classifier: Operating System :: OS Independent
Requires-Python: >=3.6
License-File: LICENSE
Requires-Dist: biopython
Requires-Dist: requests
Requires-Dist: numpy
